[
  {
    "id": 1,
    "name": "Alpha",
    "dns": "dns-a.example.com",
    "environment": "Dev",
    "endDate": "21/11/2021, 02:33 a.m.",
    "description": "Development server Alpha"
  },
  {
    "id": 2,
    "name": "Bravo",
    "dns": "dns-b.example.com",
    "environment": "QA",
    "endDate": "19/08/2020, 06:29 p.m.",
    "description": "QA server Bravo"
  },
  {
    "id": 3,
    "name": "Charlie",
    "dns": "dns-c.example.com",
    "environment": "Prod",
    "endDate": "15/07/2022, 10:00 a.m.",
    "description": "Production server Charlie"
  },
  {
    "id": 4,
    "name": "Delta",
    "dns": "dns-d.example.com",
    "environment": "Staging",
    "endDate": "10/01/2023, 09:15 a.m.",
    "description": "Staging server Delta"
  },
  {
    "id": 5,
    "name": "Echo",
    "dns": "dns-e.example.com",
    "environment": "Dev",
    "endDate": "05/03/2024, 11:45 p.m.",
    "description": "Development server Echo"
  },
  {
    "id": 6,
    "name": "Foxtrot",
    "dns": "dns-f.example.com",
    "environment": "QA",
    "endDate": "04/02/2023, 10:30 p.m.",
    "description": "QA server Foxtrot"
  },
  {
    "id": 7,
    "name": "Golf",
    "dns": "dns-g.example.com",
    "environment": "Prod",
    "endDate": "03/01/2022, 09:15 a.m.",
    "description": "Production server Golf"
  },
  {
    "id": 8,
    "name": "Hotel",
    "dns": "dns-h.example.com",
    "environment": "Staging",
    "endDate": "02/12/2023, 08:00 a.m.",
    "description": "Staging server Hotel"
  },
  {
    "id": 9,
    "name": "India",
    "dns": "dns-i.example.com",
    "environment": "Dev",
    "endDate": "01/11/2024, 06:45 p.m.",
    "description": "Development server India"
  },
  {
    "id": 10,
    "name": "Juliett",
    "dns": "dns-j.example.com",
    "environment": "QA",
    "endDate": "31/09/2023, 05:30 a.m.",
    "description": "QA server Juliett"
  },
  {
    "id": 11,
    "name": "Kilo",
    "dns": "dns-k.example.com",
    "environment": "Prod",
    "endDate": "30/08/2022, 04:15 p.m.",
    "description": "Production server Kilo"
  },
  {
    "id": 12,
    "name": "Lima",
    "dns": "dns-l.example.com",
    "environment": "Staging",
    "endDate": "29/07/2023, 03:00 a.m.",
    "description": "Staging server Lima"
  },
  {
    "id": 13,
    "name": "Mike",
    "dns": "dns-m.example.com",
    "environment": "Dev",
    "endDate": "28/06/2024, 01:45 p.m.",
    "description": "Development server Mike"
  },
  {
    "id": 14,
    "name": "November",
    "dns": "dns-n.example.com",
    "environment": "QA",
    "endDate": "27/05/2023, 12:30 a.m.",
    "description": "QA server November"
  },
  {
    "id": 15,
    "name": "Oscar",
    "dns": "dns-o.example.com",
    "environment": "Prod",
    "endDate": "26/04/2022, 11:15 p.m.",
    "description": "Production server Oscar"
  },
  {
    "id": 16,
    "name": "Papa",
    "dns": "dns-p.example.com",
    "environment": "Staging",
    "endDate": "25/03/2023, 10:00 a.m.",
    "description": "Staging server Papa"
  },
  {
    "id": 17,
    "name": "Quebec",
    "dns": "dns-q.example.com",
    "environment": "Dev",
    "endDate": "24/02/2024, 08:45 p.m.",
    "description": "Development server Quebec"
  },
  {
    "id": 18,
    "name": "Romeo",
    "dns": "dns-r.example.com",
    "environment": "QA",
    "endDate": "23/01/2023, 07:30 a.m.",
    "description": "QA server Romeo"
  },
  {
    "id": 19,
    "name": "Sierra",
    "dns": "dns-s.example.com",
    "environment": "Prod",
    "endDate": "22/12/2022, 06:15 p.m.",
    "description": "Production server Sierra"
  },
  {
    "id": 20,
    "name": "Tango",
    "dns": "dns-t.example.com",
    "environment": "Staging",
    "endDate": "21/11/2023, 05:00 a.m.",
    "description": "Staging server Tango"
  },
  {
    "id": 21,
    "name": "Uniform",
    "dns": "dns-u.example.com",
    "environment": "Dev",
    "endDate": "20/10/2024, 03:45 p.m.",
    "description": "Development server Uniform"
  },
  {
    "id": 22,
    "name": "Victor",
    "dns": "dns-v.example.com",
    "environment": "QA",
    "endDate": "19/09/2023, 02:30 a.m.",
    "description": "QA server Victor"
  },
  {
    "id": 23,
    "name": "Whiskey",
    "dns": "dns-w.example.com",
    "environment": "Prod",
    "endDate": "18/08/2022, 01:15 p.m.",
    "description": "Production server Whiskey"
  },
  {
    "id": 24,
    "name": "X-ray",
    "dns": "dns-x.example.com",
    "environment": "Staging",
    "endDate": "17/07/2023, 12:00 a.m.",
    "description": "Staging server X-ray"
  },
  {
    "id": 25,
    "name": "Yankee",
    "dns": "dns-y.example.com",
    "environment": "Dev",
    "endDate": "15/06/2024, 10:45 p.m.",
    "description": "Development server Yankee"
  },
  {
    "id": 26,
    "name": "Zulu",
    "dns": "dns-z.example.com",
    "environment": "QA",
    "endDate": "14/05/2023, 09:30 a.m.",
    "description": "QA server Zulu"
  },
  {
    "id": 27,
    "name": "AlphaBravo",
    "dns": "dns-ab.example.com",
    "environment": "Prod",
    "endDate": "13/04/2022, 08:15 p.m.",
    "description": "Production server AlphaBravo"
  },
  {
    "id": 28,
    "name": "CharlieDelta",
    "dns": "dns-cd.example.com",
    "environment": "Staging",
    "endDate": "12/03/2023, 07:00 a.m.",
    "description": "Staging server CharlieDelta"
  },
  {
    "id": 29,
    "name": "EchoFoxtrot",
    "dns": "dns-ef.example.com",
    "environment": "Dev",
    "endDate": "10/02/2024, 05:45 p.m.",
    "description": "Development server EchoFoxtrot"
  },
  {
    "id": 30,
    "name": "GolfHotel",
    "dns": "dns-gh.example.com",
    "environment": "QA",
    "endDate": "09/01/2023, 04:30 a.m.",
    "description": "QA server GolfHotel"
  },
  {
    "id": 31,
    "name": "IndiaJuliett",
    "dns": "dns-ij.example.com",
    "environment": "Prod",
    "endDate": "08/12/2022, 03:15 p.m.",
    "description": "Production server IndiaJuliett"
  },
  {
    "id": 32,
    "name": "KiloLima",
    "dns": "dns-kl.example.com",
    "environment": "Staging",
    "endDate": "07/11/2023, 02:00 a.m.",
    "description": "Staging server KiloLima"
  },
  {
    "id": 33,
    "name": "MikeNovember",
    "dns": "dns-mn.example.com",
    "environment": "Dev",
    "endDate": "06/10/2024, 12:45 p.m.",
    "description": "Development server MikeNovember"
  },
  {
    "id": 34,
    "name": "OscarPapa",
    "dns": "dns-op.example.com",
    "environment": "QA",
    "endDate": "05/09/2023, 11:30 p.m.",
    "description": "QA server OscarPapa"
  },
  {
    "id": 35,
    "name": "QuebecRomeo",
    "dns": "dns-qr.example.com",
    "environment": "Prod",
    "endDate": "04/08/2022, 10:15 a.m.",
    "description": "Production server QuebecRomeo"
  },
  {
    "id": 36,
    "name": "SierraTango",
    "dns": "dns-st.example.com",
    "environment": "Staging",
    "endDate": "03/07/2023, 09:00 p.m.",
    "description": "Staging server SierraTango"
  },
  {
    "id": 37,
    "name": "UniformVictor",
    "dns": "dns-uv.example.com",
    "environment": "Dev",
    "endDate": "02/06/2024, 07:45 a.m.",
    "description": "Development server UniformVictor"
  },
  {
    "id": 38,
    "name": "WhiskeyX-ray",
    "dns": "dns-wx.example.com",
    "environment": "QA",
    "endDate": "01/05/2023, 06:30 p.m.",
    "description": "QA server WhiskeyX-ray"
  },
  {
    "id": 39,
    "name": "ZuluAlpha",
    "dns": "dns-za.example.com",
    "environment": "Prod",
    "endDate": "30/03/2022, 05:15 a.m.",
    "description": "Production server ZuluAlpha"
  },
  {
    "id": 40,
    "name": "BravoCharlie",
    "dns": "dns-bc.example.com",
    "environment": "Staging",
    "endDate": "29/02/2024, 04:00 p.m.",
    "description": "Staging server BravoCharlie"
  },
  {
    "id": 41,
    "name": "DeltaEcho",
    "dns": "dns-de.example.com",
    "environment": "Dev",
    "endDate": "28/01/2023, 02:45 a.m.",
    "description": "Development server DeltaEcho"
  },
  {
    "id": 42,
    "name": "FoxtrotGolf",
    "dns": "dns-fg.example.com",
    "environment": "QA",
    "endDate": "27/12/2022, 01:30 p.m.",
    "description": "QA server FoxtrotGolf"
  },
  {
    "id": 43,
    "name": "HotelIndia",
    "dns": "dns-hi.example.com",
    "environment": "Prod",
    "endDate": "26/11/2023, 12:15 a.m.",
    "description": "Production server HotelIndia"
  },
  {
    "id": 44,
    "name": "JuliettKilo",
    "dns": "dns-jk.example.com",
    "environment": "Staging",
    "endDate": "25/10/2022, 11:00 p.m.",
    "description": "Staging server JuliettKilo"
  },
  {
    "id": 45,
    "name": "LimaMike",
    "dns": "dns-lm.example.com",
    "environment": "Dev",
    "endDate": "24/09/2024, 09:45 a.m.",
    "description": "Development server LimaMike"
  },
  {
    "id": 46,
    "name": "NovemberOscar",
    "dns": "dns-no.example.com",
    "environment": "QA",
    "endDate": "23/08/2023, 08:30 p.m.",
    "description": "QA server NovemberOscar"
  },
  {
    "id": 47,
    "name": "PapaQuebec",
    "dns": "dns-pq.example.com",
    "environment": "Prod",
    "endDate": "22/07/2022, 07:15 a.m.",
    "description": "Production server PapaQuebec"
  },
  {
    "id": 48,
    "name": "RomeoSierra",
    "dns": "dns-rs.example.com",
    "environment": "Staging",
    "endDate": "21/06/2023, 06:00 p.m.",
    "description": "Staging server RomeoSierra"
  },
  {
    "id": 49,
    "name": "TangoUniform",
    "dns": "dns-tu.example.com",
    "environment": "Dev",
    "endDate": "20/05/2024, 04:45 a.m.",
    "description": "Development server TangoUniform"
  },
  {
    "id": 50,
    "name": "VictorWhiskey",
    "dns": "dns-vw.example.com",
    "environment": "QA",
    "endDate": "19/04/2023, 03:30 p.m.",
    "description": "QA server VictorWhiskey"
  },
  {
    "id": 51,
    "name": "X-rayZulu",
    "dns": "dns-xz.example.com",
    "environment": "Prod",
    "endDate": "18/03/2022, 02:15 a.m.",
    "description": "Production server X-rayZulu"
  },
  {
    "id": 52,
    "name": "AlphaCharlie",
    "dns": "dns-ac.example.com",
    "environment": "Staging",
    "endDate": "17/02/2024, 01:00 p.m.",
    "description": "Staging server AlphaCharlie"
  },
  {
    "id": 53,
    "name": "BravoDelta",
    "dns": "dns-bd.example.com",
    "environment": "Dev",
    "endDate": "16/01/2023, 11:45 p.m.",
    "description": "Development server BravoDelta"
  },
  {
    "id": 54,
    "name": "EchoFoxtrot",
    "dns": "dns-ef.example.com",
    "environment": "QA",
    "endDate": "15/12/2022, 10:30 a.m.",
    "description": "QA server EchoFoxtrot"
  },
  {
    "id": 55,
    "name": "GolfHotel",
    "dns": "dns-gh.example.com",
    "environment": "Prod",
    "endDate": "14/11/2023, 09:15 p.m.",
    "description": "Production server GolfHotel"
  },
  {
    "id": 56,
    "name": "IndiaJuliett",
    "dns": "dns-ij.example.com",
    "environment": "Staging",
    "endDate": "13/10/2022, 08:00 a.m.",
    "description": "Staging server IndiaJuliett"
  },
  {
    "id": 57,
    "name": "KiloLima",
    "dns": "dns-kl.example.com",
    "environment": "Dev",
    "endDate": "12/09/2024, 06:45 p.m.",
    "description": "Development server KiloLima"
  },
  {
    "id": 58,
    "name": "MikeNovember",
    "dns": "dns-mn.example.com",
    "environment": "QA",
    "endDate": "11/08/2023, 05:30 a.m.",
    "description": "QA server MikeNovember"
  },
  {
    "id": 59,
    "name": "OscarPapa",
    "dns": "dns-op.example.com",
    "environment": "Prod",
    "endDate": "10/07/2022, 04:15 p.m.",
    "description": "Production server OscarPapa"
  },
  {
    "id": 60,
    "name": "QuebecRomeo",
    "dns": "dns-qr.example.com",
    "environment": "Staging",
    "endDate": "09/06/2023, 03:00 a.m.",
    "description": "Staging server QuebecRomeo"
  },
  {
    "id": 61,
    "name": "SierraTango",
    "dns": "dns-st.example.com",
    "environment": "Dev",
    "endDate": "08/05/2024, 01:45 p.m.",
    "description": "Development server SierraTango"
  },
  {
    "id": 62,
    "name": "UniformVictor",
    "dns": "dns-uv.example.com",
    "environment": "QA",
    "endDate": "07/04/2023, 12:30 a.m.",
    "description": "QA server UniformVictor"
  },
  {
    "id": 63,
    "name": "WhiskeyX-ray",
    "dns": "dns-wx.example.com",
    "environment": "Prod",
    "endDate": "06/03/2022, 11:15 p.m.",
    "description": "Production server WhiskeyX-ray"
  },
  {
    "id": 64,
    "name": "ZuluAlpha",
    "dns": "dns-za.example.com",
    "environment": "Staging",
    "endDate": "05/02/2024, 10:00 a.m.",
    "description": "Staging server ZuluAlpha"
  },
  {
    "id": 65,
    "name": "AlphaBravo",
    "dns": "dns-ab.example.com",
    "environment": "Dev",
    "endDate": "04/01/2023, 08:45 p.m.",
    "description": "Development server AlphaBravo"
  },
  {
    "id": 66,
    "name": "CharlieDelta",
    "dns": "dns-cd.example.com",
    "environment": "QA",
    "endDate": "03/12/2022, 07:30 a.m.",
    "description": "QA server CharlieDelta"
  },
  {
    "id": 67,
    "name": "EchoFoxtrot",
    "dns": "dns-ef.example.com",
    "environment": "Prod",
    "endDate": "02/11/2023, 06:15 p.m.",
    "description": "Production server EchoFoxtrot"
  },
  {
    "id": 68,
    "name": "GolfHotel",
    "dns": "dns-gh.example.com",
    "environment": "Staging",
    "endDate": "01/10/2022, 05:00 a.m.",
    "description": "Staging server GolfHotel"
  },
  {
    "id": 69,
    "name": "IndiaJuliett",
    "dns": "dns-ij.example.com",
    "environment": "Dev",
    "endDate": "30/08/2024, 03:45 p.m.",
    "description": "Development server IndiaJuliett"
  },
  {
    "id": 70,
    "name": "KiloLima",
    "dns": "dns-kl.example.com",
    "environment": "QA",
    "endDate": "29/07/2023, 02:30 a.m.",
    "description": "QA server KiloLima"
  },
  {
    "id": 71,
    "name": "MikeNovember",
    "dns": "dns-mn.example.com",
    "environment": "Prod",
    "endDate": "28/06/2022, 01:15 p.m.",
    "description": "Production server MikeNovember"
  },
  {
    "id": 72,
    "name": "OscarPapa",
    "dns": "dns-op.example.com",
    "environment": "Staging",
    "endDate": "27/05/2023, 12:00 a.m.",
    "description": "Staging server OscarPapa"
  },
  {
    "id": 73,
    "name": "QuebecRomeo",
    "dns": "dns-qr.example.com",
    "environment": "Dev",
    "endDate": "26/04/2024, 10:45 p.m.",
    "description": "Development server QuebecRomeo"
  },
  {
    "id": 74,
    "name": "SierraTango",
    "dns": "dns-st.example.com",
    "environment": "QA",
    "endDate": "25/03/2023, 09:30 a.m.",
    "description": "QA server SierraTango"
  },
  {
    "id": 75,
    "name": "UniformVictor",
    "dns": "dns-uv.example.com",
    "environment": "Prod",
    "endDate": "24/02/2022, 08:15 p.m.",
    "description": "Production server UniformVictor"
  },
  {
    "id": 76,
    "name": "WhiskeyX-ray",
    "dns": "dns-wx.example.com",
    "environment": "Staging",
    "endDate": "23/01/2024, 07:00 a.m.",
    "description": "Staging server WhiskeyX-ray"
  },
  {
    "id": 77,
    "name": "ZuluAlpha",
    "dns": "dns-za.example.com",
    "environment": "Dev",
    "endDate": "22/12/2023, 05:45 p.m.",
    "description": "Development server ZuluAlpha"
  },
  {
    "id": 78,
    "name": "AlphaBravo",
    "dns": "dns-ab.example.com",
    "environment": "QA",
    "endDate": "21/11/2022, 04:30 a.m.",
    "description": "QA server AlphaBravo"
  },
  {
    "id": 79,
    "name": "CharlieDelta",
    "dns": "dns-cd.example.com",
    "environment": "Prod",
    "endDate": "20/10/2023, 03:15 p.m.",
    "description": "Production server CharlieDelta"
  },
  {
    "id": 80,
    "name": "EchoFoxtrot",
    "dns": "dns-ef.example.com",
    "environment": "Staging",
    "endDate": "19/09/2022, 02:00 a.m.",
    "description": "Staging server EchoFoxtrot"
  },
  {
    "id": 81,
    "name": "GolfHotel",
    "dns": "dns-gh.example.com",
    "environment": "Dev",
    "endDate": "18/08/2024, 12:45 p.m.",
    "description": "Development server GolfHotel"
  },
  {
    "id": 82,
    "name": "IndiaJuliett",
    "dns": "dns-ij.example.com",
    "environment": "QA",
    "endDate": "17/07/2023, 11:30 p.m.",
    "description": "QA server IndiaJuliett"
  },
  {
    "id": 83,
    "name": "KiloLima",
    "dns": "dns-kl.example.com",
    "environment": "Prod",
    "endDate": "16/06/2022, 10:15 a.m.",
    "description": "Production server KiloLima"
  },
  {
    "id": 84,
    "name": "MikeNovember",
    "dns": "dns-mn.example.com",
    "environment": "Staging",
    "endDate": "15/05/2024, 09:00 p.m.",
    "description": "Staging server MikeNovember"
  },
  {
    "id": 85,
    "name": "OscarPapa",
    "dns": "dns-op.example.com",
    "environment": "Dev",
    "endDate": "14/04/2023, 07:45 a.m.",
    "description": "Development server OscarPapa"
  },
  {
    "id": 86,
    "name": "QuebecRomeo",
    "dns": "dns-qr.example.com",
    "environment": "QA",
    "endDate": "13/03/2022, 06:30 p.m.",
    "description": "QA server QuebecRomeo"
  },
  {
    "id": 87,
    "name": "SierraTango",
    "dns": "dns-st.example.com",
    "environment": "Prod",
    "endDate": "12/02/2024, 05:15 a.m.",
    "description": "Production server SierraTango"
  },
  {
    "id": 88,
    "name": "UniformVictor",
    "dns": "dns-uv.example.com",
    "environment": "Staging",
    "endDate": "11/01/2023, 04:00 p.m.",
    "description": "Staging server UniformVictor"
  },
  {
    "id": 89,
    "name": "WhiskeyX-ray",
    "dns": "dns-wx.example.com",
    "environment": "Dev",
    "endDate": "10/12/2024, 02:45 a.m.",
    "description": "Development server WhiskeyX-ray"
  },
  {
    "id": 90,
    "name": "ZuluAlpha",
    "dns": "dns-za.example.com",
    "environment": "QA",
    "endDate": "09/11/2023, 01:30 p.m.",
    "description": "QA server ZuluAlpha"
  },
  {
    "id": 91,
    "name": "AlphaBravo",
    "dns": "dns-ab.example.com",
    "environment": "Prod",
    "endDate": "08/10/2022, 12:15 a.m.",
    "description": "Production server AlphaBravo"
  },
  {
    "id": 92,
    "name": "CharlieDelta",
    "dns": "dns-cd.example.com",
    "environment": "Staging",
    "endDate": "07/09/2023, 11:00 p.m.",
    "description": "Staging server CharlieDelta"
  },
  {
    "id": 93,
    "name": "EchoFoxtrot",
    "dns": "dns-ef.example.com",
    "environment": "Dev",
    "endDate": "06/08/2024, 09:45 a.m.",
    "description": "Development server EchoFoxtrot"
  },
  {
    "id": 94,
    "name": "GolfHotel",
    "dns": "dns-gh.example.com",
    "environment": "QA",
    "endDate": "05/07/2023, 08:30 p.m.",
    "description": "QA server GolfHotel"
  },
  {
    "id": 95,
    "name": "IndiaJuliett",
    "dns": "dns-ij.example.com",
    "environment": "Prod",
    "endDate": "04/06/2022, 07:15 a.m.",
    "description": "Production server IndiaJuliett"
  },
  {
    "id": 96,
    "name": "KiloLima",
    "dns": "dns-kl.example.com",
    "environment": "Staging",
    "endDate": "03/05/2024, 06:00 p.m.",
    "description": "Staging server KiloLima"
  },
  {
    "id": 97,
    "name": "MikeNovember",
    "dns": "dns-mn.example.com",
    "environment": "Dev",
    "endDate": "02/04/2023, 04:45 a.m.",
    "description": "Development server MikeNovember"
  },
  {
    "id": 98,
    "name": "NovemberOscar",
    "dns": "dns-no.example.com",
    "environment": "QA",
    "endDate": "01/03/2022, 03:30 p.m.",
    "description": "QA server NovemberOscar"
  },
  {
    "id": 99,
    "name": "PapaQuebec",
    "dns": "dns-pq.example.com",
    "environment": "Prod",
    "endDate": "28/02/2024, 02:15 a.m.",
    "description": "Production server PapaQuebec"
  },
  {
    "id": 100,
    "name": "RomeoSierra",
    "dns": "dns-rs.example.com",
    "environment": "Staging",
    "endDate": "27/01/2023, 01:00 p.m.",
    "description": "Staging server RomeoSierra"
  },
  {
    "id": 101,
    "name": "TangoUniform",
    "dns": "dns-tu.example.com",
    "environment": "Dev",
    "endDate": "26/12/2024, 11:45 p.m.",
    "description": "Development server TangoUniform"
  },
  {
    "id": 102,
    "name": "VictorWhiskey",
    "dns": "dns-vw.example.com",
    "environment": "QA",
    "endDate": "25/11/2023, 10:30 a.m.",
    "description": "QA server VictorWhiskey"
  },
  {
    "id": 103,
    "name": "X-rayZulu",
    "dns": "dns-xz.example.com",
    "environment": "Prod",
    "endDate": "24/10/2022, 09:15 p.m.",
    "description": "Production server X-rayZulu"
  },
  {
    "id": 104,
    "name": "AlphaCharlie",
    "dns": "dns-ac.example.com",
    "environment": "Staging",
    "endDate": "23/09/2023, 08:00 a.m.",
    "description": "Staging server AlphaCharlie"
  },
  {
    "id": 105,
    "name": "BravoDelta",
    "dns": "dns-bd.example.com",
    "environment": "Dev",
    "endDate": "22/08/2024, 06:45 p.m.",
    "description": "Development server BravoDelta"
  },
  {
    "id": 106,
    "name": "CharlieEcho",
    "dns": "dns-ce.example.com",
    "environment": "QA",
    "endDate": "21/07/2023, 05:30 a.m.",
    "description": "QA server CharlieEcho"
  },
  {
    "id": 107,
    "name": "FoxtrotGolf",
    "dns": "dns-fg.example.com",
    "environment": "Prod",
    "endDate": "20/06/2022, 04:15 p.m.",
    "description": "Production server FoxtrotGolf"
  },
  {
    "id": 108,
    "name": "HotelIndia",
    "dns": "dns-hi.example.com",
    "environment": "Staging",
    "endDate": "19/05/2023, 03:00 a.m.",
    "description": "Staging server HotelIndia"
  },
  {
    "id": 109,
    "name": "JuliettKilo",
    "dns": "dns-jk.example.com",
    "environment": "Dev",
    "endDate": "18/04/2024, 01:45 p.m.",
    "description": "Development server JuliettKilo"
  },
  {
    "id": 110,
    "name": "KiloLima",
    "dns": "dns-kl.example.com",
    "environment": "QA",
    "endDate": "17/03/2023, 12:30 a.m.",
    "description": "QA server KiloLima"
  },
  {
    "id": 111,
    "name": "MikeNovember",
    "dns": "dns-mn.example.com",
    "environment": "Prod",
    "endDate": "16/02/2022, 11:15 p.m.",
    "description": "Production server MikeNovember"
  },
  {
    "id": 112,
    "name": "NovemberOscar",
    "dns": "dns-no.example.com",
    "environment": "Staging",
    "endDate": "15/01/2024, 10:00 a.m.",
    "description": "Staging server NovemberOscar"
  },
  {
    "id": 113,
    "name": "PapaQuebec",
    "dns": "dns-pq.example.com",
    "environment": "Dev",
    "endDate": "14/12/2023, 08:45 p.m.",
    "description": "Development server PapaQuebec"
  },
  {
    "id": 114,
    "name": "RomeoSierra",
    "dns": "dns-rs.example.com",
    "environment": "QA",
    "endDate": "13/11/2022, 07:30 p.m.",
    "description": "QA server RomeoSierra"
  },
  {
    "id": 115,
    "name": "TangoUniform",
    "dns": "dns-tu.example.com",
    "environment": "Prod",
    "endDate": "12/10/2024, 06:15 p.m.",
    "description": "Production server TangoUniform"
  },
  {
    "id": 116,
    "name": "VictorWhiskey",
    "dns": "dns-vw.example.com",
    "environment": "Staging",
    "endDate": "11/09/2023, 05:00 a.m.",
    "description": "Staging server VictorWhiskey"
  },
  {
    "id": 117,
    "name": "X-rayZulu",
    "dns": "dns-xz.example.com",
    "environment": "Dev",
    "endDate": "10/08/2022, 03:45 p.m.",
    "description": "Development server X-rayZulu"
  },
  {
    "id": 118,
    "name": "AlphaBravo",
    "dns": "dns-ab.example.com",
    "environment": "QA",
    "endDate": "09/07/2024, 02:30 a.m.",
    "description": "QA server AlphaBravo"
  },
  {
    "id": 119,
    "name": "CharlieDelta",
    "dns": "dns-cd.example.com",
    "environment": "Prod",
    "endDate": "08/06/2023, 01:15 p.m.",
    "description": "Production server CharlieDelta"
  },
  {
    "id": 120,
    "name": "EchoFoxtrot",
    "dns": "dns-ef.example.com",
    "environment": "Staging",
    "endDate": "07/05/2022, 12:00 a.m.",
    "description": "Staging server EchoFoxtrot"
  },
  {
    "id": 121,
    "name": "GolfHotel",
    "dns": "dns-gh.example.com",
    "environment": "Dev",
    "endDate": "06/04/2024, 10:45 p.m.",
    "description": "Development server GolfHotel"
  },
  {
    "id": 122,
    "name": "IndiaJuliett",
    "dns": "dns-ij.example.com",
    "environment": "QA",
    "endDate": "05/03/2023, 09:30 a.m.",
    "description": "QA server IndiaJuliett"
  },
  {
    "id": 123,
    "name": "KiloLima",
    "dns": "dns-kl.example.com",
    "environment": "Prod",
    "endDate": "04/02/2022, 08:15 p.m.",
    "description": "Production server KiloLima"
  },
  {
    "id": 124,
    "name": "MikeNovember",
    "dns": "dns-mn.example.com",
    "environment": "Staging",
    "endDate": "03/01/2024, 07:00 a.m.",
    "description": "Staging server MikeNovember"
  },
  {
    "id": 125,
    "name": "NovemberOscar",
    "dns": "dns-no.example.com",
    "environment": "Dev",
    "endDate": "02/12/2023, 05:45 p.m.",
    "description": "Development server NovemberOscar"
  },
  {
    "id": 126,
    "name": "PapaQuebec",
    "dns": "dns-pq.example.com",
    "environment": "QA",
    "endDate": "01/11/2022, 04:30 a.m.",
    "description": "QA server PapaQuebec"
  },
  {
    "id": 127,
    "name": "RomeoSierra",
    "dns": "dns-rs.example.com",
    "environment": "Prod",
    "endDate": "31/10/2023, 03:15 p.m.",
    "description": "Production server RomeoSierra"
  },
  {
    "id": 128,
    "name": "TangoUniform",
    "dns": "dns-tu.example.com",
    "environment": "Staging",
    "endDate": "30/09/2024, 02:00 a.m.",
    "description": "Staging server TangoUniform"
  },
  {
    "id": 129,
    "name": "VictorWhiskey",
    "dns": "dns-vw.example.com",
    "environment": "Dev",
    "endDate": "29/08/2023, 12:45 p.m.",
    "description": "Development server VictorWhiskey"
  },
  {
    "id": 130,
    "name": "X-rayZulu",
    "dns": "dns-xz.example.com",
    "environment": "QA",
    "endDate": "28/07/2022, 11:30 p.m.",
    "description": "QA server X-rayZulu"
  },
  {
    "id": 131,
    "name": "AlphaBravo",
    "dns": "dns-ab.example.com",
    "environment": "Prod",
    "endDate": "27/06/2024, 10:15 a.m.",
    "description": "Production server AlphaBravo"
  },
  {
    "id": 132,
    "name": "CharlieDelta",
    "dns": "dns-cd.example.com",
    "environment": "Staging",
    "endDate": "26/05/2023, 09:00 p.m.",
    "description": "Staging server CharlieDelta"
  },
  {
    "id": 133,
    "name": "EchoFoxtrot",
    "dns": "dns-ef.example.com",
    "environment": "Dev",
    "endDate": "25/04/2024, 07:45 a.m.",
    "description": "Development server EchoFoxtrot"
  },
  {
    "id": 134,
    "name": "GolfHotel",
    "dns": "dns-gh.example.com",
    "environment": "QA",
    "endDate": "24/03/2023, 06:30 p.m.",
    "description": "QA server GolfHotel"
  },
  {
    "id": 135,
    "name": "IndiaJuliett",
    "dns": "dns-ij.example.com",
    "environment": "Prod",
    "endDate": "23/02/2022, 05:15 a.m.",
    "description": "Production server IndiaJuliett"
  },
  {
    "id": 136,
    "name": "KiloLima",
    "dns": "dns-kl.example.com",
    "environment": "Staging",
    "endDate": "22/01/2024, 04:00 p.m.",
    "description": "Staging server KiloLima"
  },
  {
    "id": 137,
    "name": "MikeNovember",
    "dns": "dns-mn.example.com",
    "environment": "Dev",
    "endDate": "21/12/2023, 02:45 a.m.",
    "description": "Development server MikeNovember"
  },
  {
    "id": 138,
    "name": "NovemberOscar",
    "dns": "dns-no.example.com",
    "environment": "QA",
    "endDate": "20/11/2022, 01:30 p.m.",
    "description": "QA server NovemberOscar"
  },
  {
    "id": 139,
    "name": "PapaQuebec",
    "dns": "dns-pq.example.com",
    "environment": "Prod",
    "endDate": "19/10/2024, 12:15 a.m.",
    "description": "Production server PapaQuebec"
  },
  {
    "id": 140,
    "name": "RomeoSierra",
    "dns": "dns-rs.example.com",
    "environment": "Staging",
    "endDate": "18/09/2023, 11:00 p.m.",
    "description": "Staging server RomeoSierra"
  },
  {
    "id": 141,
    "name": "TangoUniform",
    "dns": "dns-tu.example.com",
    "environment": "Dev",
    "endDate": "17/08/2024, 09:45 a.m.",
    "description": "Development server TangoUniform"
  },
  {
    "id": 142,
    "name": "VictorWhiskey",
    "dns": "dns-vw.example.com",
    "environment": "QA",
    "endDate": "16/07/2023, 08:30 p.m.",
    "description": "QA server VictorWhiskey"
  },
  {
    "id": 143,
    "name": "X-rayZulu",
    "dns": "dns-xz.example.com",
    "environment": "Prod",
    "endDate": "15/06/2022, 07:15 a.m.",
    "description": "Production server X-rayZulu"
  },
  {
    "id": 144,
    "name": "AlphaBravo",
    "dns": "dns-ab.example.com",
    "environment": "Staging",
    "endDate": "14/05/2024, 06:00 p.m.",
    "description": "Staging server AlphaBravo"
  },
  {
    "id": 145,
    "name": "CharlieDelta",
    "dns": "dns-cd.example.com",
    "environment": "Dev",
    "endDate": "13/04/2023, 04:45 a.m.",
    "description": "Development server CharlieDelta"
  },
  {
    "id": 146,
    "name": "EchoFoxtrot",
    "dns": "dns-ef.example.com",
    "environment": "QA",
    "endDate": "12/03/2024, 03:30 p.m.",
    "description": "QA server EchoFoxtrot"
  },
  {
    "id": 147,
    "name": "GolfHotel",
    "dns": "dns-gh.example.com",
    "environment": "Prod",
    "endDate": "11/02/2023, 02:15 a.m.",
    "description": "Production server GolfHotel"
  },
  {
    "id": 148,
    "name": "IndiaJuliett",
    "dns": "dns-ij.example.com",
    "environment": "Staging",
    "endDate": "10/01/2024, 01:00 p.m.",
    "description": "Staging server IndiaJuliett"
  },
  {
    "id": 149,
    "name": "KiloLima",
    "dns": "dns-kl.example.com",
    "environment": "Dev",
    "endDate": "09/12/2023, 11:45 p.m.",
    "description": "Development server KiloLima"
  },
  {
    "id": 150,
    "name": "MikeNovember",
    "dns": "dns-mn.example.com",
    "environment": "QA",
    "endDate": "08/11/2022, 10:30 a.m.",
    "description": "QA server MikeNovember"
  },
  {
    "id": 151,
    "name": "NovemberOscar",
    "dns": "dns-no.example.com",
    "environment": "Prod",
    "endDate": "07/10/2024, 09:15 p.m.",
    "description": "Production server NovemberOscar"
  },
  {
    "id": 152,
    "name": "PapaQuebec",
    "dns": "dns-pq.example.com",
    "environment": "Staging",
    "endDate": "06/09/2023, 08:00 a.m.",
    "description": "Staging server PapaQuebec"
  },
  {
    "id": 153,
    "name": "RomeoSierra",
    "dns": "dns-rs.example.com",
    "environment": "Dev",
    "endDate": "05/08/2024, 06:45 p.m.",
    "description": "Development server RomeoSierra"
  },
  {
    "id": 154,
    "name": "TangoUniform",
    "dns": "dns-tu.example.com",
    "environment": "QA",
    "endDate": "04/07/2023, 05:30 a.m.",
    "description": "QA server TangoUniform"
  },
  {
    "id": 155,
    "name": "X-rayZulu",
    "dns": "dns-xz.example.com",
    "environment": "Prod",
    "endDate": "03/06/2022, 04:15 p.m.",
    "description": "Production server X-rayZulu"
  },
  {
    "id": 156,
    "name": "AlphaBravo",
    "dns": "dns-ab.example.com",
    "environment": "Staging",
    "endDate": "02/05/2024, 03:00 a.m.",
    "description": "Staging server AlphaBravo"
  },
  {
    "id": 157,
    "name": "CharlieDelta",
    "dns": "dns-cd.example.com",
    "environment": "Dev",
    "endDate": "01/04/2023, 01:45 p.m.",
    "description": "Development server CharlieDelta"
  },
  {
    "id": 158,
    "name": "EchoFoxtrot",
    "dns": "dns-ef.example.com",
    "environment": "QA",
    "endDate": "31/03/2024, 12:30 a.m.",
    "description": "QA server EchoFoxtrot"
  },
  {
    "id": 159,
    "name": "GolfHotel",
    "dns": "dns-gh.example.com",
    "environment": "Prod",
    "endDate": "30/01/2023, 11:15 p.m.",
    "description": "Production server GolfHotel"
  },
  {
    "id": 160,
    "name": "IndiaJuliett",
    "dns": "dns-ij.example.com",
    "environment": "Staging",
    "endDate": "29/12/2024, 10:00 a.m.",
    "description": "Staging server IndiaJuliett"
  },
  {
    "id": 161,
    "name": "KiloLima",
    "dns": "dns-kl.example.com",
    "environment": "Dev",
    "endDate": "28/11/2023, 08:45 p.m.",
    "description": "Development server KiloLima"
  },
  {
    "id": 162,
    "name": "MikeNovember",
    "dns": "dns-mn.example.com",
    "environment": "QA",
    "endDate": "27/10/2022, 07:30 p.m.",
    "description": "QA server MikeNovember"
  },
  {
    "id": 163,
    "name": "NovemberOscar",
    "dns": "dns-no.example.com",
    "environment": "Prod",
    "endDate": "26/09/2024, 06:15 p.m.",
    "description": "Production server NovemberOscar"
  },
  {
    "id": 164,
    "name": "PapaQuebec",
    "dns": "dns-pq.example.com",
    "environment": "Staging",
    "endDate": "25/08/2023, 05:00 a.m.",
    "description": "Staging server PapaQuebec"
  },
  {
    "id": 165,
    "name": "RomeoSierra",
    "dns": "dns-rs.example.com",
    "environment": "Dev",
    "endDate": "24/07/2024, 03:45 p.m.",
    "description": "Development server RomeoSierra"
  },
  {
    "id": 166,
    "name": "TangoUniform",
    "dns": "dns-tu.example.com",
    "environment": "QA",
    "endDate": "23/06/2023, 02:30 a.m.",
    "description": "QA server TangoUniform"
  },
  {
    "id": 167,
    "name": "X-rayZulu",
    "dns": "dns-xz.example.com",
    "environment": "Prod",
    "endDate": "22/05/2022, 01:15 p.m.",
    "description": "Production server X-rayZulu"
  },
  {
    "id": 168,
    "name": "AlphaBravo",
    "dns": "dns-ab.example.com",
    "environment": "Staging",
    "endDate": "21/04/2024, 12:00 a.m.",
    "description": "Staging server AlphaBravo"
  },
  {
    "id": 169,
    "name": "CharlieDelta",
    "dns": "dns-cd.example.com",
    "environment": "Dev",
    "endDate": "20/03/2023, 10:45 p.m.",
    "description": "Development server CharlieDelta"
  },
  {
    "id": 170,
    "name": "EchoFoxtrot",
    "dns": "dns-ef.example.com",
    "environment": "QA",
    "endDate": "19/02/2024, 09:30 a.m.",
    "description": "QA server EchoFoxtrot"
  },
  {
    "id": 171,
    "name": "GolfHotel",
    "dns": "dns-gh.example.com",
    "environment": "Prod",
    "endDate": "18/01/2023, 08:15 p.m.",
    "description": "Production server GolfHotel"
  },
  {
    "id": 172,
    "name": "IndiaJuliett",
    "dns": "dns-ij.example.com",
    "environment": "Staging",
    "endDate": "17/12/2024, 07:00 a.m.",
    "description": "Staging server IndiaJuliett"
  },
  {
    "id": 173,
    "name": "KiloLima",
    "dns": "dns-kl.example.com",
    "environment": "Dev",
    "endDate": "16/11/2023, 05:45 p.m.",
    "description": "Development server KiloLima"
  },
  {
    "id": 174,
    "name": "MikeNovember",
    "dns": "dns-mn.example.com",
    "environment": "QA",
    "endDate": "15/10/2022, 04:30 p.m.",
    "description": "QA server MikeNovember"
  },
  {
    "id": 175,
    "name": "NovemberOscar",
    "dns": "dns-no.example.com",
    "environment": "Prod",
    "endDate": "14/09/2024, 03:15 p.m.",
    "description": "Production server NovemberOscar"
  },
  {
    "id": 176,
    "name": "PapaQuebec",
    "dns": "dns-pq.example.com",
    "environment": "Staging",
    "endDate": "13/08/2023, 02:00 a.m.",
    "description": "Staging server PapaQuebec"
  },
  {
    "id": 177,
    "name": "RomeoSierra",
    "dns": "dns-rs.example.com",
    "environment": "Dev",
    "endDate": "12/07/2024, 12:45 p.m.",
    "description": "Development server RomeoSierra"
  },
  {
    "id": 178,
    "name": "TangoUniform",
    "dns": "dns-tu.example.com",
    "environment": "QA",
    "endDate": "11/06/2023, 11:30 p.m.",
    "description": "QA server TangoUniform"
  },
  {
    "id": 179,
    "name": "X-rayZulu",
    "dns": "dns-xz.example.com",
    "environment": "Prod",
    "endDate": "10/05/2022, 10:15 a.m.",
    "description": "Production server X-rayZulu"
  },
  {
    "id": 180,
    "name": "AlphaBravo",
    "dns": "dns-ab.example.com",
    "environment": "Staging",
    "endDate": "09/04/2024, 09:00 p.m.",
    "description": "Staging server AlphaBravo"
  },
  {
    "id": 181,
    "name": "CharlieDelta",
    "dns": "dns-cd.example.com",
    "environment": "Dev",
    "endDate": "08/03/2023, 07:45 a.m.",
    "description": "Development server CharlieDelta"
  },
  {
    "id": 182,
    "name": "EchoFoxtrot",
    "dns": "dns-ef.example.com",
    "environment": "QA",
    "endDate": "07/02/2024, 06:30 p.m.",
    "description": "QA server EchoFoxtrot"
  },
  {
    "id": 183,
    "name": "GolfHotel",
    "dns": "dns-gh.example.com",
    "environment": "Prod",
    "endDate": "06/01/2023, 05:15 a.m.",
    "description": "Production server GolfHotel"
  },
  {
    "id": 184,
    "name": "IndiaJuliett",
    "dns": "dns-ij.example.com",
    "environment": "Staging",
    "endDate": "05/12/2024, 04:00 p.m.",
    "description": "Staging server IndiaJuliett"
  },
  {
    "id": 185,
    "name": "KiloLima",
    "dns": "dns-kl.example.com",
    "environment": "Dev",
    "endDate": "04/11/2023, 02:45 a.m.",
    "description": "Development server KiloLima"
  },
  {
    "id": 186,
    "name": "MikeNovember",
    "dns": "dns-mn.example.com",
    "environment": "QA",
    "endDate": "03/10/2022, 01:30 p.m.",
    "description": "QA server MikeNovember"
  },
  {
    "id": 187,
    "name": "NovemberOscar",
    "dns": "dns-no.example.com",
    "environment": "Prod",
    "endDate": "02/09/2024, 12:15 a.m.",
    "description": "Production server NovemberOscar"
  },
  {
    "id": 188,
    "name": "PapaQuebec",
    "dns": "dns-pq.example.com",
    "environment": "Staging",
    "endDate": "01/08/2023, 11:00 p.m.",
    "description": "Staging server PapaQuebec"
  },
  {
    "id": 189,
    "name": "RomeoSierra",
    "dns": "dns-rs.example.com",
    "environment": "Dev",
    "endDate": "31/07/2024, 09:45 a.m.",
    "description": "Development server RomeoSierra"
  },
  {
    "id": 190,
    "name": "TangoUniform",
    "dns": "dns-tu.example.com",
    "environment": "QA",
    "endDate": "30/06/2023, 08:30 p.m.",
    "description": "QA server TangoUniform"
  },
  {
    "id": 191,
    "name": "X-rayZulu",
    "dns": "dns-xz.example.com",
    "environment": "Prod",
    "endDate": "29/05/2022, 07:15 a.m.",
    "description": "Production server X-rayZulu"
  },
  {
    "id": 192,
    "name": "AlphaBravo",
    "dns": "dns-ab.example.com",
    "environment": "Staging",
    "endDate": "28/04/2024, 06:00 p.m.",
    "description": "Staging server AlphaBravo"
  },
  {
    "id": 193,
    "name": "CharlieDelta",
    "dns": "dns-cd.example.com",
    "environment": "Dev",
    "endDate": "27/03/2023, 04:45 a.m.",
    "description": "Development server CharlieDelta"
  },
  {
    "id": 194,
    "name": "EchoFoxtrot",
    "dns": "dns-ef.example.com",
    "environment": "QA",
    "endDate": "26/02/2024, 03:30 p.m.",
    "description": "QA server EchoFoxtrot"
  },
  {
    "id": 195,
    "name": "GolfHotel",
    "dns": "dns-gh.example.com",
    "environment": "Prod",
    "endDate": "25/01/2023, 02:15 a.m.",
    "description": "Production server GolfHotel"
  },
  {
    "id": 196,
    "name": "IndiaJuliett",
    "dns": "dns-ij.example.com",
    "environment": "Staging",
    "endDate": "24/12/2024, 01:00 p.m.",
    "description": "Staging server IndiaJuliett"
  },
  {
    "id": 197,
    "name": "KiloLima",
    "dns": "dns-kl.example.com",
    "environment": "Dev",
    "endDate": "23/11/2023, 11:45 p.m.",
    "description": "Development server KiloLima"
  },
  {
    "id": 198,
    "name": "MikeNovember",
    "dns": "dns-mn.example.com",
    "environment": "QA",
    "endDate": "22/10/2022, 10:30 a.m.",
    "description": "QA server MikeNovember"
  },
  {
    "id": 199,
    "name": "NovemberOscar",
    "dns": "dns-no.example.com",
    "environment": "Prod",
    "endDate": "21/09/2024, 09:15 p.m.",
    "description": "Production server NovemberOscar"
  },
  {
    "id": 200,
    "name": "PapaQuebec",
    "dns": "dns-pq.example.com",
    "environment": "Staging",
    "endDate": "20/08/2023, 08:00 a.m.",
    "description": "Staging server PapaQuebec"
  },
  {
    "id": 201,
    "name": "RomeoSierra",
    "dns": "dns-rs.example.com",
    "environment": "Dev",
    "endDate": "19/07/2024, 06:45 p.m.",
    "description": "Development server RomeoSierra"
  },
  {
    "id": 202,
    "name": "TangoUniform",
    "dns": "dns-tu.example.com",
    "environment": "QA",
    "endDate": "18/06/2023, 05:30 a.m.",
    "description": "QA server TangoUniform"
  },
  {
    "id": 203,
    "name": "X-rayZulu",
    "dns": "dns-xz.example.com",
    "environment": "Prod",
    "endDate": "17/05/2022, 04:15 p.m.",
    "description": "Production server X-rayZulu"
  },
  {
    "id": 204,
    "name": "AlphaBravo",
    "dns": "dns-ab.example.com",
    "environment": "Staging",
    "endDate": "16/04/2024, 03:00 a.m.",
    "description": "Staging server AlphaBravo"
  },
  {
    "id": 205,
    "name": "CharlieDelta",
    "dns": "dns-cd.example.com",
    "environment": "Dev",
    "endDate": "15/03/2023, 01:45 p.m.",
    "description": "Development server CharlieDelta"
  },
  {
    "id": 206,
    "name": "EchoFoxtrot",
    "dns": "dns-ef.example.com",
    "environment": "QA",
    "endDate": "14/02/2024, 12:30 p.m.",
    "description": "QA server EchoFoxtrot"
  },
  {
    "id": 207,
    "name": "GolfHotel",
    "dns": "dns-gh.example.com",
    "environment": "Prod",
    "endDate": "13/01/2023, 11:15 p.m.",
    "description": "Production server GolfHotel"
  },
  {
    "id": 208,
    "name": "IndiaJuliett",
    "dns": "dns-ij.example.com",
    "environment": "Staging",
    "endDate": "12/12/2024, 10:00 a.m.",
    "description": "Staging server IndiaJuliett"
  },
  {
    "id": 209,
    "name": "KiloLima",
    "dns": "dns-kl.example.com",
    "environment": "Dev",
    "endDate": "11/11/2023, 08:45 p.m.",
    "description": "Development server KiloLima"
  },
  {
    "id": 210,
    "name": "MikeNovember",
    "dns": "dns-mn.example.com",
    "environment": "QA",
    "endDate": "10/10/2022, 07:30 p.m.",
    "description": "QA server MikeNovember"
  },
  {
    "id": 211,
    "name": "NovemberOscar",
    "dns": "dns-no.example.com",
    "environment": "Prod",
    "endDate": "09/09/2024, 06:15 p.m.",
    "description": "Production server NovemberOscar"
  },
  {
    "id": 212,
    "name": "PapaQuebec",
    "dns": "dns-pq.example.com",
    "environment": "Staging",
    "endDate": "08/08/2023, 05:00 a.m.",
    "description": "Staging server PapaQuebec"
  },
  {
    "id": 213,
    "name": "RomeoSierra",
    "dns": "dns-rs.example.com",
    "environment": "Dev",
    "endDate": "07/07/2024, 03:45 p.m.",
    "description": "Development server RomeoSierra"
  },
  {
    "id": 214,
    "name": "TangoUniform",
    "dns": "dns-tu.example.com",
    "environment": "QA",
    "endDate": "06/06/2023, 02:30 a.m.",
    "description": "QA server TangoUniform"
  },
  {
    "id": 215,
    "name": "X-rayZulu",
    "dns": "dns-xz.example.com",
    "environment": "Prod",
    "endDate": "05/05/2022, 01:15 p.m.",
    "description": "Production server X-rayZulu"
  },
  {
    "id": 216,
    "name": "AlphaBravo",
    "dns": "dns-ab.example.com",
    "environment": "Staging",
    "endDate": "04/04/2024, 12:00 a.m.",
    "description": "Staging server AlphaBravo"
  },
  {
    "id": 217,
    "name": "CharlieDelta",
    "dns": "dns-cd.example.com",
    "environment": "Dev",
    "endDate": "03/03/2023, 10:45 p.m.",
    "description": "Development server CharlieDelta"
  },
  {
    "id": 218,
    "name": "EchoFoxtrot",
    "dns": "dns-ef.example.com",
    "environment": "QA",
    "endDate": "02/02/2024, 09:30 a.m.",
    "description": "QA server EchoFoxtrot"
  },
  {
    "id": 219,
    "name": "GolfHotel",
    "dns": "dns-gh.example.com",
    "environment": "Prod",
    "endDate": "01/01/2023, 08:15 p.m.",
    "description": "Production server GolfHotel"
  },
  {
    "id": 220,
    "name": "IndiaJuliett",
    "dns": "dns-ij.example.com",
    "environment": "Staging",
    "endDate": "31/12/2024, 07:00 a.m.",
    "description": "Staging server IndiaJuliett"
  },
  {
    "id": 221,
    "name": "KiloLima",
    "dns": "dns-kl.example.com",
    "environment": "Dev",
    "endDate": "30/11/2023, 05:45 p.m.",
    "description": "Development server KiloLima"
  },
  {
    "id": 222,
    "name": "MikeNovember",
    "dns": "dns-mn.example.com",
    "environment": "QA",
    "endDate": "29/10/2022, 04:30 p.m.",
    "description": "QA server MikeNovember"
  },
  {
    "id": 223,
    "name": "NovemberOscar",
    "dns": "dns-no.example.com",
    "environment": "Prod",
    "endDate": "28/09/2024, 03:15 p.m.",
    "description": "Production server NovemberOscar"
  },
  {
    "id": 224,
    "name": "PapaQuebec",
    "dns": "dns-pq.example.com",
    "environment": "Staging",
    "endDate": "27/08/2023, 02:00 a.m.",
    "description": "Staging server PapaQuebec"
  },
  {
    "id": 225,
    "name": "RomeoSierra",
    "dns": "dns-rs.example.com",
    "environment": "Dev",
    "endDate": "26/07/2024, 12:45 p.m.",
    "description": "Development server RomeoSierra"
  },
  {
    "id": 226,
    "name": "TangoUniform",
    "dns": "dns-tu.example.com",
    "environment": "QA",
    "endDate": "25/06/2023, 11:30 p.m.",
    "description": "QA server TangoUniform"
  },
  {
    "id": 227,
    "name": "X-rayZulu",
    "dns": "dns-xz.example.com",
    "environment": "Prod",
    "endDate": "24/05/2022, 10:15 a.m.",
    "description": "Production server X-rayZulu"
  },
  {
    "id": 228,
    "name": "AlphaBravo",
    "dns": "dns-ab.example.com",
    "environment": "Staging",
    "endDate": "23/04/2024, 09:00 p.m.",
    "description": "Staging server AlphaBravo"
  },
  {
    "id": 229,
    "name": "CharlieDelta",
    "dns": "dns-cd.example.com",
    "environment": "Dev",
    "endDate": "22/03/2023, 07:45 a.m.",
    "description": "Development server CharlieDelta"
  },
  {
    "id": 230,
    "name": "EchoFoxtrot",
    "dns": "dns-ef.example.com",
    "environment": "QA",
    "endDate": "21/02/2024, 06:30 p.m.",
    "description": "QA server EchoFoxtrot"
  },
  {
    "id": 231,
    "name": "GolfHotel",
    "dns": "dns-gh.example.com",
    "environment": "Prod",
    "endDate": "20/01/2023, 05:15 a.m.",
    "description": "Production server GolfHotel"
  },
  {
    "id": 232,
    "name": "IndiaJuliett",
    "dns": "dns-ij.example.com",
    "environment": "Staging",
    "endDate": "19/12/2024, 04:00 p.m.",
    "description": "Staging server IndiaJuliett"
  },
  {
    "id": 233,
    "name": "KiloLima",
    "dns": "dns-kl.example.com",
    "environment": "Dev",
    "endDate": "18/11/2023, 02:45 a.m.",
    "description": "Development server KiloLima"
  },
  {
    "id": 234,
    "name": "MikeNovember",
    "dns": "dns-mn.example.com",
    "environment": "QA",
    "endDate": "17/10/2022, 01:30 p.m.",
    "description": "QA server MikeNovember"
  },
  {
    "id": 235,
    "name": "NovemberOscar",
    "dns": "dns-no.example.com",
    "environment": "Prod",
    "endDate": "16/09/2024, 12:15 a.m.",
    "description": "Production server NovemberOscar"
  },
  {
    "id": 236,
    "name": "PapaQuebec",
    "dns": "dns-pq.example.com",
    "environment": "Staging",
    "endDate": "15/08/2023, 11:00 p.m.",
    "description": "Staging server PapaQuebec"
  },
  {
    "id": 237,
    "name": "RomeoSierra",
    "dns": "dns-rs.example.com",
    "environment": "Dev",
    "endDate": "14/07/2024, 09:45 a.m.",
    "description": "Development server RomeoSierra"
  },
  {
    "id": 238,
    "name": "TangoUniform",
    "dns": "dns-tu.example.com",
    "environment": "QA",
    "endDate": "13/06/2023, 08:30 p.m.",
    "description": "QA server TangoUniform"
  },
  {
    "id": 239,
    "name": "X-rayZulu",
    "dns": "dns-xz.example.com",
    "environment": "Prod",
    "endDate": "12/05/2022, 07:15 a.m.",
    "description": "Production server X-rayZulu"
  },
  {
    "id": 240,
    "name": "AlphaBravo",
    "dns": "dns-ab.example.com",
    "environment": "Staging",
    "endDate": "11/04/2024, 06:00 p.m.",
    "description": "Staging server AlphaBravo"
  },
  {
    "id": 241,
    "name": "CharlieDelta",
    "dns": "dns-cd.example.com",
    "environment": "Dev",
    "endDate": "10/03/2023, 04:45 a.m.",
    "description": "Development server CharlieDelta"
  },
  {
    "id": 242,
    "name": "EchoFoxtrot",
    "dns": "dns-ef.example.com",
    "environment": "QA",
    "endDate": "09/02/2024, 03:30 p.m.",
    "description": "QA server EchoFoxtrot"
  },
  {
    "id": 243,
    "name": "GolfHotel",
    "dns": "dns-gh.example.com",
    "environment": "Prod",
    "endDate": "08/01/2023, 02:15 a.m.",
    "description": "Production server GolfHotel"
  },
  {
    "id": 244,
    "name": "IndiaJuliett",
    "dns": "dns-ij.example.com",
    "environment": "Staging",
    "endDate": "07/12/2024, 01:00 p.m.",
    "description": "Staging server IndiaJuliett"
  },
  {
    "id": 245,
    "name": "KiloLima",
    "dns": "dns-kl.example.com",
    "environment": "Dev",
    "endDate": "06/11/2023, 11:45 p.m.",
    "description": "Development server KiloLima"
  },
  {
    "id": 246,
    "name": "MikeNovember",
    "dns": "dns-mn.example.com",
    "environment": "QA",
    "endDate": "05/10/2022, 10:30 a.m.",
    "description": "QA server MikeNovember"
  },
  {
    "id": 247,
    "name": "NovemberOscar",
    "dns": "dns-no.example.com",
    "environment": "Prod",
    "endDate": "04/09/2024, 09:15 p.m.",
    "description": "Production server NovemberOscar"
  },
  {
    "id": 248,
    "name": "PapaQuebec",
    "dns": "dns-pq.example.com",
    "environment": "Staging",
    "endDate": "03/08/2023, 08:00 a.m.",
    "description": "Staging server PapaQuebec"
  },
  {
    "id": 249,
    "name": "RomeoSierra",
    "dns": "dns-rs.example.com",
    "environment": "Dev",
    "endDate": "02/07/2024, 06:45 p.m.",
    "description": "Development server RomeoSierra"
  },
  {
    "id": 250,
    "name": "TangoUniform",
    "dns": "dns-tu.example.com",
    "environment": "QA",
    "endDate": "01/06/2023, 05:30 a.m.",
    "description": "QA server TangoUniform"
  },
  {
    "id": 251,
    "name": "X-rayZulu",
    "dns": "dns-xz.example.com",
    "environment": "Prod",
    "endDate": "31/05/2022, 04:15 p.m.",
    "description": "Production server X-rayZulu"
  },
  {
    "id": 252,
    "name": "AlphaBravo",
    "dns": "dns-ab.example.com",
    "environment": "Staging",
    "endDate": "30/04/2024, 03:00 a.m.",
    "description": "Staging server AlphaBravo"
  },
  {
    "id": 253,
    "name": "CharlieDelta",
    "dns": "dns-cd.example.com",
    "environment": "Dev",
    "endDate": "29/03/2023, 01:45 p.m.",
    "description": "Development server CharlieDelta"
  },
  {
    "id": 254,
    "name": "EchoFoxtrot",
    "dns": "dns-ef.example.com",
    "environment": "QA",
    "endDate": "28/02/2024, 12:30 p.m.",
    "description": "QA server EchoFoxtrot"
  },
  {
    "id": 255,
    "name": "GolfHotel",
    "dns": "dns-gh.example.com",
    "environment": "Prod",
    "endDate": "27/01/2023, 11:15 p.m.",
    "description": "Production server GolfHotel"
  },
  {
    "id": 256,
    "name": "IndiaJuliett",
    "dns": "dns-ij.example.com",
    "environment": "Staging",
    "endDate": "26/12/2024, 10:00 a.m.",
    "description": "Staging server IndiaJuliett"
  },
  {
    "id": 257,
    "name": "KiloLima",
    "dns": "dns-kl.example.com",
    "environment": "Dev",
    "endDate": "25/11/2023, 08:45 p.m.",
    "description": "Development server KiloLima"
  },
  {
    "id": 258,
    "name": "MikeNovember",
    "dns": "dns-mn.example.com",
    "environment": "QA",
    "endDate": "24/10/2022, 07:30 p.m.",
    "description": "QA server MikeNovember"
  },
  {
    "id": 259,
    "name": "NovemberOscar",
    "dns": "dns-no.example.com",
    "environment": "Prod",
    "endDate": "23/09/2024, 06:15 p.m.",
    "description": "Production server NovemberOscar"
  },
  {
    "id": 260,
    "name": "PapaQuebec",
    "dns": "dns-pq.example.com",
    "environment": "Staging",
    "endDate": "22/08/2023, 05:00 a.m.",
    "description": "Staging server PapaQuebec"
  },
  {
    "id": 261,
    "name": "RomeoSierra",
    "dns": "dns-rs.example.com",
    "environment": "Dev",
    "endDate": "21/07/2024, 03:45 p.m.",
    "description": "Development server RomeoSierra"
  },
  {
    "id": 262,
    "name": "TangoUniform",
    "dns": "dns-tu.example.com",
    "environment": "QA",
    "endDate": "20/06/2023, 02:30 a.m.",
    "description": "QA server TangoUniform"
  },
  {
    "id": 263,
    "name": "X-rayZulu",
    "dns": "dns-xz.example.com",
    "environment": "Prod",
    "endDate": "19/05/2022, 01:15 p.m.",
    "description": "Production server X-rayZulu"
  },
  {
    "id": 264,
    "name": "AlphaBravo",
    "dns": "dns-ab.example.com",
    "environment": "Staging",
    "endDate": "18/04/2024, 12:00 a.m.",
    "description": "Staging server AlphaBravo"
  },
  {
    "id": 265,
    "name": "CharlieDelta",
    "dns": "dns-cd.example.com",
    "environment": "Dev",
    "endDate": "17/03/2023, 10:45 p.m.",
    "description": "Development server CharlieDelta"
  },
  {
    "id": 266,
    "name": "EchoFoxtrot",
    "dns": "dns-ef.example.com",
    "environment": "QA",
    "endDate": "16/02/2024, 09:30 a.m.",
    "description": "QA server EchoFoxtrot"
  },
  {
    "id": 267,
    "name": "GolfHotel",
    "dns": "dns-gh.example.com",
    "environment": "Prod",
    "endDate": "15/01/2023, 08:15 p.m.",
    "description": "Production server GolfHotel"
  },
  {
    "id": 268,
    "name": "IndiaJuliett",
    "dns": "dns-ij.example.com",
    "environment": "Staging",
    "endDate": "14/12/2024, 07:00 a.m.",
    "description": "Staging server IndiaJuliett"
  },
  {
    "id": 269,
    "name": "KiloLima",
    "dns": "dns-kl.example.com",
    "environment": "Dev",
    "endDate": "13/11/2023, 05:45 p.m.",
    "description": "Development server KiloLima"
  },
  {
    "id": 270,
    "name": "MikeNovember",
    "dns": "dns-mn.example.com",
    "environment": "QA",
    "endDate": "12/10/2022, 04:30 p.m.",
    "description": "QA server MikeNovember"
  },
  {
    "id": 271,
    "name": "NovemberOscar",
    "dns": "dns-no.example.com",
    "environment": "Prod",
    "endDate": "11/09/2024, 03:15 p.m.",
    "description": "Production server NovemberOscar"
  },
  {
    "id": 272,
    "name": "PapaQuebec",
    "dns": "dns-pq.example.com",
    "environment": "Staging",
    "endDate": "10/08/2023, 02:00 a.m.",
    "description": "Staging server PapaQuebec"
  },
  {
    "id": 273,
    "name": "RomeoSierra",
    "dns": "dns-rs.example.com",
    "environment": "Dev",
    "endDate": "09/07/2024, 12:45 p.m.",
    "description": "Development server RomeoSierra"
  },
  {
    "id": 274,
    "name": "TangoUniform",
    "dns": "dns-tu.example.com",
    "environment": "QA",
    "endDate": "08/06/2023, 11:30 p.m.",
    "description": "QA server TangoUniform"
  },
  {
    "id": 275,
    "name": "X-rayZulu",
    "dns": "dns-xz.example.com",
    "environment": "Prod",
    "endDate": "07/05/2022, 10:15 a.m.",
    "description": "Production server X-rayZulu"
  },
  {
    "id": 276,
    "name": "AlphaBravo",
    "dns": "dns-ab.example.com",
    "environment": "Staging",
    "endDate": "06/04/2024, 09:00 p.m.",
    "description": "Staging server AlphaBravo"
  },
  {
    "id": 277,
    "name": "CharlieDelta",
    "dns": "dns-cd.example.com",
    "environment": "Dev",
    "endDate": "05/03/2023, 07:45 a.m.",
    "description": "Development server CharlieDelta"
  },
  {
    "id": 278,
    "name": "EchoFoxtrot",
    "dns": "dns-ef.example.com",
    "environment": "QA",
    "endDate": "04/02/2024, 06:30 p.m.",
    "description": "QA server EchoFoxtrot"
  },
  {
    "id": 279,
    "name": "GolfHotel",
    "dns": "dns-gh.example.com",
    "environment": "Prod",
    "endDate": "03/01/2023, 05:15 a.m.",
    "description": "Production server GolfHotel"
  },
  {
    "id": 280,
    "name": "IndiaJuliett",
    "dns": "dns-ij.example.com",
    "environment": "Staging",
    "endDate": "02/12/2024, 04:00 p.m.",
    "description": "Staging server IndiaJuliett"
  },
  {
    "id": 281,
    "name": "KiloLima",
    "dns": "dns-kl.example.com",
    "environment": "Dev",
    "endDate": "01/11/2023, 02:45 a.m.",
    "description": "Development server KiloLima"
  },
  {
    "id": 282,
    "name": "MikeNovember",
    "dns": "dns-mn.example.com",
    "environment": "QA",
    "endDate": "31/10/2022, 01:30 p.m.",
    "description": "QA server MikeNovember"
  },
  {
    "id": 283,
    "name": "NovemberOscar",
    "dns": "dns-no.example.com",
    "environment": "Prod",
    "endDate": "30/09/2024, 12:15 a.m.",
    "description": "Production server NovemberOscar"
  },
  {
    "id": 284,
    "name": "PapaQuebec",
    "dns": "dns-pq.example.com",
    "environment": "Staging",
    "endDate": "29/08/2023, 11:00 p.m.",
    "description": "Staging server PapaQuebec"
  },
  {
    "id": 285,
    "name": "RomeoSierra",
    "dns": "dns-rs.example.com",
    "environment": "Dev",
    "endDate": "28/07/2024, 09:45 a.m.",
    "description": "Development server RomeoSierra"
  },
  {
    "id": 286,
    "name": "TangoUniform",
    "dns": "dns-tu.example.com",
    "environment": "QA",
    "endDate": "27/06/2023, 08:30 p.m.",
    "description": "QA server TangoUniform"
  },
  {
    "id": 287,
    "name": "X-rayZulu",
    "dns": "dns-xz.example.com",
    "environment": "Prod",
    "endDate": "26/05/2022, 07:15 a.m.",
    "description": "Production server X-rayZulu"
  },
  {
    "id": 288,
    "name": "AlphaBravo",
    "dns": "dns-ab.example.com",
    "environment": "Staging",
    "endDate": "25/04/2024, 06:00 p.m.",
    "description": "Staging server AlphaBravo"
  },
  {
    "id": 289,
    "name": "CharlieDelta",
    "dns": "dns-cd.example.com",
    "environment": "Dev",
    "endDate": "24/03/2023, 04:45 a.m.",
    "description": "Development server CharlieDelta"
  },
  {
    "id": 290,
    "name": "EchoFoxtrot",
    "dns": "dns-ef.example.com",
    "environment": "QA",
    "endDate": "23/02/2024, 03:30 p.m.",
    "description": "QA server EchoFoxtrot"
  },
  {
    "id": 291,
    "name": "GolfHotel",
    "dns": "dns-gh.example.com",
    "environment": "Prod",
    "endDate": "22/01/2023, 02:15 a.m.",
    "description": "Production server GolfHotel"
  },
  {
    "id": 292,
    "name": "IndiaJuliett",
    "dns": "dns-ij.example.com",
    "environment": "Staging",
    "endDate": "21/12/2024, 01:00 p.m.",
    "description": "Staging server IndiaJuliett"
  },
  {
    "id": 293,
    "name": "KiloLima",
    "dns": "dns-kl.example.com",
    "environment": "Dev",
    "endDate": "20/11/2023, 11:45 p.m.",
    "description": "Development server KiloLima"
  },
  {
    "id": 294,
    "name": "MikeNovember",
    "dns": "dns-mn.example.com",
    "environment": "QA",
    "endDate": "19/10/2022, 10:30 a.m.",
    "description": "QA server MikeNovember"
  },
  {
    "id": 295,
    "name": "NovemberOscar",
    "dns": "dns-no.example.com",
    "environment": "Prod",
    "endDate": "18/09/2024, 09:15 p.m.",
    "description": "Production server NovemberOscar"
  },
  {
    "id": 296,
    "name": "PapaQuebec",
    "dns": "dns-pq.example.com",
    "environment": "Staging",
    "endDate": "17/08/2023, 08:00 a.m.",
    "description": "Staging server PapaQuebec"
  },
  {
    "id": 297,
    "name": "RomeoSierra",
    "dns": "dns-rs.example.com",
    "environment": "Dev",
    "endDate": "16/07/2024, 06:45 p.m.",
    "description": "Development server RomeoSierra"
  },
  {
    "id": 298,
    "name": "TangoUniform",
    "dns": "dns-tu.example.com",
    "environment": "QA",
    "endDate": "15/06/2023, 05:30 a.m.",
    "description": "QA server TangoUniform"
  },
  {
    "id": 299,
    "name": "X-rayZulu",
    "dns": "dns-xz.example.com",
    "environment": "Prod",
    "endDate": "14/05/2022, 04:15 p.m.",
    "description": "Production server X-rayZulu"
  },
  {
    "id": 300,
    "name": "AlphaBravo",
    "dns": "dns-ab.example.com",
    "environment": "Staging",
    "endDate": "13/04/2024, 03:00 a.m.",
    "description": "Staging server AlphaBravo"
  }
]